arxivtrends/__init__.py
arxivtrends/arxivtrends.py
arxivtrends/graphics.py
arxivtrends/methods.py
Arxivtrends-0.0.2.dist-info/LICENSE
Arxivtrends-0.0.2.dist-info/METADATA
Arxivtrends-0.0.2.dist-info/WHEEL
Arxivtrends-0.0.2.dist-info/top_level.txt
Arxivtrends-0.0.2.dist-info/RECORD
